autoshopify.py
autoshopify-0.1.0.dist-info/METADATA
autoshopify-0.1.0.dist-info/WHEEL
autoshopify-0.1.0.dist-info/entry_points.txt
autoshopify-0.1.0.dist-info/top_level.txt
autoshopify-0.1.0.dist-info/RECORD
