Metadata-Version: 2.4
Name: autoshopify
Version: 0.1.0
Summary: Autoshopify CLI + library
Author: Darkboy
License: MIT
Requires-Python: >=3.8
Requires-Dist: requests
